multigit/__init__.py
multigit/__main__.py
multigit/gitrepo.py
multigit/subrepofile.py
multigit/subrepos.py
multigit/subrepos_schema.yaml
multigit-0.11.8.dist-info/METADATA
multigit-0.11.8.dist-info/WHEEL
multigit-0.11.8.dist-info/entry_points.txt
multigit-0.11.8.dist-info/licenses/LICENSE
multigit-0.11.8.dist-info/RECORD
